realoot-1.0.2.dist-info/WHEEL
realoot-1.0.2.dist-info/RECORD
realoot-1.0.2.dist-info/top_level.txt
realoot-1.0.2.dist-info/METADATA
realoot/README.md
realoot/__init__.py
realoot/LICENSE.md
realoot/main/__init__.py
realoot/main/_constants.so
realoot/main/_main.so
realoot/examples/_ex1.py
realoot/examples/_ex3.py
realoot/examples/ex2.xml
realoot/examples/__init__.py
realoot/examples/_ex2.py
realoot/utils/__init__.py
realoot.libs/libboost_python37-4b12c13c.so.1.72.0
realoot.libs/libxerces-c-3-530182c4.0.so
realoot.libs/libboost_system-34e6a7b7.so.1.72.0
