Metadata-Version: 2.1
Name: realoot
Version: 1.0.2
Summary: Solve the averaged low-thrust optimal control transfer problem
Home-page: https://gitlab.com/jorispio/realoot
Author: Joris T. OLYMPIO
Author-email: jto.devs@gmail.com
License: GPLv3
Keywords: "optimal control" "space trajectory" orbit
Platform: UNKNOWN
Classifier: Development Status :: 4 - Beta
Classifier: Intended Audience :: Science/Research
Classifier: Topic :: Scientific/Engineering
Classifier: License :: OSI Approved :: GNU General Public License v3 (GPLv3)
Classifier: Programming Language :: Python :: 3
Classifier: Programming Language :: Python :: 3.7
Classifier: Programming Language :: Python :: 3.8
Requires-Python: >=3.7
